sweego/__init__.py
sweego/api_client.py
sweego/api_response.py
sweego/configuration.py
sweego/exceptions.py
sweego/rest.py
sweego/api/__init__.py
sweego/api/auth_api.py
sweego/api/billing_api.py
sweego/api/channels_api.py
sweego/api/client_api.py
sweego/api/client_api_key_api.py
sweego/api/client_billing_api.py
sweego/api/client_credentials_api.py
sweego/api/client_domain_api.py
sweego/api/client_mta_server_api.py
sweego/api/client_sftp_server_api.py
sweego/api/client_template_api.py
sweego/api/client_template_variable_api.py
sweego/api/client_user_api.py
sweego/api/default_api.py
sweego/api/image_hosting_api.py
sweego/api/logs_api.py
sweego/api/send_api.py
sweego/api/stats_api.py
sweego/api/webhook_api.py
sweego/models/__init__.py
sweego/models/api_key_creation_response.py
sweego/models/api_key_get_response.py
sweego/models/api_key_list_response.py
sweego/models/associated_api_key.py
sweego/models/associated_credential.py
sweego/models/base_response.py
sweego/models/billing_country.py
sweego/models/billing_plan.py
sweego/models/billing_plan_checkout.py
sweego/models/billing_plan_feature_data.py
sweego/models/billing_plan_info.py
sweego/models/billing_plan_subscription_started.py
sweego/models/channel.py
sweego/models/channel_consumption_quota.py
sweego/models/channel_type.py
sweego/models/client_api_credentials_creation.py
sweego/models/client_api_key_creation.py
sweego/models/client_api_key_enabled.py
sweego/models/client_api_key_update_scope.py
sweego/models/client_billing_coupon_is_valid.py
sweego/models/client_billing_invoice.py
sweego/models/client_billing_quota_state.py
sweego/models/client_created.py
sweego/models/client_credential_enabled.py
sweego/models/client_credential_update_scope.py
sweego/models/client_dns_record.py
sweego/models/client_domain.py
sweego/models/client_domain_check_response.py
sweego/models/client_domain_creation.py
sweego/models/client_domain_creation_response.py
sweego/models/client_domain_info_response.py
sweego-0.0.1.dist-info/METADATA
sweego-0.0.1.dist-info/WHEEL
sweego-0.0.1.dist-info/top_level.txt
sweego-0.0.1.dist-info/RECORD
